typedprotocol/__init__.py
typedprotocol/method_checker.py
typedprotocol/protocol.py
typedprotocol/substitution.py
typedprotocol/type_checker.py
typedprotocol-0.1.0.dist-info/METADATA
typedprotocol-0.1.0.dist-info/WHEEL
typedprotocol-0.1.0.dist-info/licenses/LICENSE
typedprotocol-0.1.0.dist-info/RECORD
