Metadata-Version: 2.4
Name: typedprotocol
Version: 0.1.0
Summary: Typed protocols with runtime validation and structural typing
Project-URL: Homepage, https://github.com/okanakbulut/typedprotocol
Project-URL: Bug Reports, https://github.com/okanakbulut/typedprotocol/issues
Project-URL: Source, https://github.com/okanakbulut/typedprotocol
Project-URL: Documentation, https://github.com/okanakbulut/typedprotocol#readme
Author: Okan Akbulut
Maintainer: Okan Akbulut
License: MIT
License-File: LICENSE
Keywords: protocols,runtime,structural,typing,validation
Classifier: Development Status :: 4 - Beta
Classifier: Intended Audience :: Developers
Classifier: License :: OSI Approved :: MIT License
Classifier: Operating System :: OS Independent
Classifier: Programming Language :: Python :: 3
Classifier: Programming Language :: Python :: 3.12
Classifier: Programming Language :: Python :: 3.13
Classifier: Programming Language :: Python :: 3.14
Classifier: Topic :: Software Development :: Libraries :: Python Modules
Classifier: Topic :: Software Development :: Quality Assurance
Classifier: Typing :: Typed
Requires-Python: >=3.12
Requires-Dist: typing-extensions>=4.15.0
